pytorch_supporter/__init__.py
pytorch_supporter/layers/__init__.py
pytorch_supporter/layers/dict_to_parameters.py
pytorch_supporter/layers/dot_product.py
pytorch_supporter/layers/gru_last_hidden_state.py
pytorch_supporter/layers/hidden_state_reset_gru.py
pytorch_supporter/layers/hidden_state_reset_lstm.py
pytorch_supporter/layers/hidden_state_reset_rnn.py
pytorch_supporter/layers/lazily_initialized_linear.py
pytorch_supporter/layers/lstm_last_hidden_state.py
pytorch_supporter/layers/permute.py
pytorch_supporter/layers/reshape.py
pytorch_supporter/layers/rnn_last_hidden_state.py
pytorch_supporter/layers/select_from_array.py
pytorch_supporter/utils/__init__.py
pytorch_supporter/utils/text.py
pytorch_supporter/utils/time_series.py
pytorch_supporter-0.0.20.dist-info/METADATA
pytorch_supporter-0.0.20.dist-info/WHEEL
pytorch_supporter-0.0.20.dist-info/top_level.txt
pytorch_supporter-0.0.20.dist-info/RECORD
