Metadata-Version: 2.1
Name: pytorch-supporter
Version: 0.0.20
Summary: Pytorch supporter
Home-page: https://github.com/automatethem/pytorch-supporter
Author: Sang Ki Kwon
Author-email: automatethem@gmail.com
License: MIT
Requires-Dist: torchsummaryX
Requires-Dist: bs4
